{
  "last_updated": 1771891227,
  "league": "Hardcore Phrecia 2.0",
  "total_players": 200,
  "players_updated": 0,
  "class_distribution": {
    "Scavenger": 1792,
    "Behemoth": 679,
    "Harbinger": 491,
    "Ancestral Commander": 5478,
    "Aristocrat": 1697,
    "Herald": 3331,
    "Polytheist": 626,
    "Daughter of Oshabi": 639,
    "Surfcaster": 518,
    "Paladin": 1558,
    "Servant of Arakaali": 1115,
    "Architect of Chaos": 261,
    "Gambler": 332,
    "Whisperer": 181,
    "Bog Shaman": 793,
    "Wildspeaker": 234,
    "Puppeteer": 255,
    "Blind Prophet": 115,
    "Antiquarian": 5
  }
}